{
    "packages":
    [
        {
            "name":"IoThingsWare",
            "maintainer":"Toni Cafiero",
            "websiteURL":"http://www.iothingsware.com",
            "email":"info@iothingsware.com",
            "help":{ "online":"http://iothingsware.com" },
            "platforms": 
            [
                {
                    "name": "TopView nRF52832 Boards (32-bits ARM Cortex-M4F)",
                    "architecture": "nRF52832",
                    "version": "0.6.0",
                    "category": "IoThingsWare",
                    "url": "https://github.com/tcafiero/IoThingsWareTools/raw/master/nRF52832-0.6.0.zip",
                    "archiveFileName": "nRF52832-0.6.0.zip",
                    "checksum": "SHA-256:88ae068b100570dd71aefd1cb281c273427b873529ffed748bf14099242f1fc0",
                    "boards":
                    [
                        {"name": "Nordic Semiconductor nRF52 DK"},
                        {"name": "TopView nRF52 Board"},
                        {"name": "RedBear Blend 2"}
                    ],
                    "toolsDependencies":
                    [
                        {
                            "packager": "IoThingsWare",
                            "name": "arm-none-eabi-gcc",
                            "version": "5_2-2015q4"
                        },
                        {
                            "packager": "IoThingsWare",
                            "name": "openocd",
                            "version": "0.10.0-dev-nrf5"
                        }
                    ]
                }				
            ],
            "tools":
            [
                {
                    "name": "arm-none-eabi-gcc",
                    "version": "5_2-2015q4",
                    "systems": 
                    [
                        {
							"host": "i686-mingw32",
							"url": "https://github.com/sandeepmistry/arduino-nRF5/releases/download/tools/gcc-arm-none-eabi-5_2-2015q4-20151219-win32.tar.bz2",
							"archiveFileName": "gcc-arm-none-eabi-5_2-2015q4-20151219-win32.tar.bz2",
							"size": "102981732",
							"checksum": "MD5:32d950225b6c7c886f6225c1fc578934"
                        },
                        {
							"host": "i386-apple-darwin11",
							"url": "https://github.com/sandeepmistry/arduino-nRF5/releases/download/tools/gcc-arm-none-eabi-5_2-2015q4-20151219-mac.tar.bz2",
							"archiveFileName": "gcc-arm-none-eabi-5_2-2015q4-20151219-mac.tar.bz2",
							"size": "96372129",
							"checksum": "MD5:603bcce8e59683ac27054b3197a53254"
                        },
                        {
							"host": "x86_64-pc-linux-gnu",
							"url": "https://github.com/sandeepmistry/arduino-nRF5/releases/download/tools/gcc-arm-none-eabi-5_2-2015q4-20151219-linux.tar.bz2",
							"archiveFileName": "gcc-arm-none-eabi-5_2-2015q4-20151219-linux.tar.bz2",
							"size": "92811866",
							"checksum": "MD5:f88caac80b4444a17344f57ccb760b90"
                        },
                        {
							"host": "i686-linux-gnu",
							"url": "https://github.com/sandeepmistry/arduino-nRF5/releases/download/tools/gcc-arm-none-eabi-5_2-2015q4-20151219-linux.tar.bz2",
							"archiveFileName": "gcc-arm-none-eabi-5_2-2015q4-20151219-linux.tar.bz2",
							"size": "92811866",
							"checksum": "MD5:f88caac80b4444a17344f57ccb760b90"
                        }
                    ]
                },
                {
                    "name": "openocd",
                    "version": "0.10.0-dev-nrf5",
                    "systems": 
                    [
                        {
                            "host": "i686-mingw32",
                            "url": "https://github.com/tcafiero/IoThingsWareTools/raw/master/openocd-0.10.0-dev-nrf5.zip",
                            "archiveFileName": "openocd-0.10.0-dev-nrf5.zip",
                            "checksum": "SHA-256:4fd616f6c9242ac287af5fdcd6e0036edc6831e76899746a0203fca2ea771492",
                            "size": "19833654"
                        }
                    ]
                },
                {
                    "name": "bossac",
                    "version": "1.3a-arduino",
                    "systems": 
                    [
                        {
                            "host": "i686-linux-gnu",
                            "url": "http://downloads.arduino.cc/tools/bossac-1.3a-arduino-i686-linux-gnu.tar.bz2",
                            "archiveFileName": "bossac-1.3a-arduino-i686-linux-gnu.tar.bz2",
                            "checksum": "SHA-256:d6d10362f40729a7877e43474fcf02ad82cf83321cc64ca931f5c82b2d25d24f",
                            "size": "147359"
                        },
                        {
                            "host": "x86_64-pc-linux-gnu",
                            "url": "http://downloads.arduino.cc/tools/bossac-1.3a-arduino-x86_64-pc-linux-gnu.tar.bz2",
                            "archiveFileName": "bossac-1.3a-arduino-x86_64-pc-linux-gnu.tar.bz2",
                            "checksum": "SHA-256:c1daed033251296768fa8b63ad283e053da93427c0f3cd476a71a9188e18442c",
                            "size": "26179"
                        },
                        {
                            "host": "i686-mingw32",
                            "url": "http://downloads.arduino.cc/tools/bossac-1.3a-arduino-i686-mingw32.tar.bz2",
                            "archiveFileName": "bossac-1.3a-arduino-i686-mingw32.tar.bz2",
                            "checksum": "SHA-256:a37727622e0f86cb4f2856ad0209568a5d804234dba3dc0778829730d61a5ec7",
                            "size": "265647"
                        },
                        {
                            "host": "i386-apple-darwin11",
                            "url": "http://downloads.arduino.cc/tools/bossac-1.3a-arduino-i386-apple-darwin11.tar.bz2",
                            "archiveFileName": "bossac-1.3a-arduino-i386-apple-darwin11.tar.bz2",
                            "checksum": "SHA-256:40770b225753e7a52bb165e8f37e6b760364f5c5e96048168d0178945bd96ad6",
                            "size": "39475"
                        }
                    ]
                },
                {
                    "name": "openocd",
                    "version": "0.10.0-dev-nrf5",
                    "systems":
                    [
                        {
                            "host": "i686-mingw32",
                            "url": "https://github.com/tcafiero/IoThingsWareTools/raw/master/openocd-0.10.0-dev-nrf5.zip",
                            "archiveFileName": "openocd-0.10.0-dev-nrf5.tar.gz",
                            "size": "19833654",
                            "checksum": "SHA-256:4fd616f6c9242ac287af5fdcd6e0036edc6831e76899746a0203fca2ea771492"
                        }
                    ]
                }                
            ]
        }
    ]
}